mara_db/__init__.py
mara_db/auto_migration.py
mara_db/bigquery.py
mara_db/cli.py
mara_db/config.py
mara_db/databricks.py
mara_db/dbs.py
mara_db/formats.py
mara_db/mysql.py
mara_db/postgresql.py
mara_db/shell.py
mara_db/sqlalchemy_engine.py
mara_db/sqlserver.py
mara_db/views.py
mara_db/static/schema-page.js
mara_db-4.11.0.dist-info/LICENSE
mara_db-4.11.0.dist-info/METADATA
mara_db-4.11.0.dist-info/WHEEL
mara_db-4.11.0.dist-info/entry_points.txt
mara_db-4.11.0.dist-info/top_level.txt
mara_db-4.11.0.dist-info/RECORD
