Metadata-Version: 2.1
Name: mara-db
Version: 4.11.0
Summary: Configuration and monitoring of database connections
Home-page: https://github.com/mara/mara-db
Author: Mara contributors
License: MIT
Requires-Python: >=3.6
License-File: LICENSE
Requires-Dist: SQLAlchemy >=1.1.5
Requires-Dist: sqlalchemy-utils >=0.32.14
Requires-Dist: alembic >=0.8.10
Requires-Dist: multimethod >=1.0.0
Requires-Dist: graphviz >=0.8
Requires-Dist: mara-page >=1.3.0
Requires-Dist: psycopg2-binary >=2.7.3
Provides-Extra: bigquery
Requires-Dist: google-cloud-bigquery ; extra == 'bigquery'
Requires-Dist: google-cloud-bigquery-storage ; extra == 'bigquery'
Requires-Dist: pyarrow ; extra == 'bigquery'
Requires-Dist: sqlalchemy-bigquery ; extra == 'bigquery'
Provides-Extra: databricks
Requires-Dist: databricks-sql-cli ; extra == 'databricks'
Requires-Dist: databricks-sql-connector ; extra == 'databricks'
Requires-Dist: sqlalchemy-databricks ; extra == 'databricks'
Provides-Extra: mssql
Requires-Dist: pyodbc ; extra == 'mssql'
Provides-Extra: mysql
Requires-Dist: mysqlclient ; extra == 'mysql'
Provides-Extra: postgres
Requires-Dist: psycopg2-binary >=2.7.3 ; extra == 'postgres'
Provides-Extra: redshift
Requires-Dist: psycopg2-binary >=2.7.3 ; extra == 'redshift'
Requires-Dist: sqlalchemy-redshift ; extra == 'redshift'
Provides-Extra: snowflake
Requires-Dist: snowflake-sqlalchemy ; extra == 'snowflake'
Provides-Extra: test
Requires-Dist: pytest ; extra == 'test'
Requires-Dist: pytest-click ; extra == 'test'
Requires-Dist: pytest-docker ; extra == 'test'
Requires-Dist: pytest-dependency ; extra == 'test'
Requires-Dist: SQLAlchemy >=1.2.0 ; extra == 'test'
